LICENSE
README.md
setup.cfg
setup.py
azpython/perp.py
azpython/spot.py
azpython.egg-info/PKG-INFO
azpython.egg-info/SOURCES.txt
azpython.egg-info/dependency_links.txt
azpython.egg-info/not-zip-safe
azpython.egg-info/requires.txt
azpython.egg-info/top_level.txt
azpython/websocket/az_websocket.py
azpython/websocket/perp.py
azpython/websocket/spot.py