Metadata-Version: 2.1
Name: azpython
Version: 0.1.1
Summary: Python3 AZ.COM HTTP API Connector
Home-page: https://github.com/selinayiya/api-python-demo
Author: az
Author-email: az@az.com
License: MIT License
Download-URL: https://github.com/selinayiya/api-python-demo/archive/refs/tags/V0.1.1.tar.gz
Keywords: az api connector
Platform: UNKNOWN
Classifier: Development Status :: 4 - Beta
Classifier: Intended Audience :: Developers
Classifier: Topic :: Software Development :: Libraries :: Python Modules
Classifier: License :: OSI Approved :: MIT License
Classifier: Programming Language :: Python :: 3.9
Classifier: Programming Language :: Python :: 3.10
Requires-Python: >=3.9
